{
    "24195243": {
        "id": 24195243,
        "topicName": "",
        "members": [
            {
                "id": "49959662-2fb9-41d1-a743-52f2feb5a772",
                "socketId": "",
                "displayName": "",
                "currentRoom": 24195243,
                "userStatus": 0,
                "permissions": {
                    "host": true
                }
            }
        ],
        "status": 0
    },
    "27662185": {
        "id": 27662185,
        "topicName": "",
        "members": [
            {
                "id": "b7b31cbd-5765-48a7-a967-a0169a4762c1",
                "socketId": "",
                "displayName": "",
                "currentRoom": 27662185,
                "userStatus": 0,
                "permissions": {
                    "host": true
                }
            }
        ],
        "status": 0
    },
    "52030757": {
        "id": 52030757,
        "topicName": "",
        "members": [
            {
                "id": "2fea383e-d58c-4bb2-9286-110b77863131",
                "socketId": "",
                "displayName": "",
                "currentRoom": 52030757,
                "userStatus": 0,
                "permissions": {
                    "host": true
                }
            },
            {
                "id": "aeb11a15-580a-4a72-8753-4383b5bfbcd0",
                "socketId": "",
                "displayName": "",
                "currentRoom": 52030757,
                "userStatus": 0,
                "permissions": {
                    "host": false
                }
            }
        ],
        "status": 0
    },
    "56643602": {
        "id": 56643602,
        "topicName": "",
        "members": [
            {
                "id": "dab688fe-bf7e-4301-9bcd-bfbd51f29506",
                "socketId": "",
                "displayName": "",
                "currentRoom": 56643602,
                "userStatus": 0,
                "permissions": {
                    "host": true
                }
            }
        ],
        "status": 0
    },
    "69763147": {
        "id": 69763147,
        "topicName": "",
        "members": [
            {
                "id": "e97adfa2-83bd-47a3-a5f6-94e295979343",
                "socketId": "",
                "displayName": "",
                "currentRoom": 69763147,
                "userStatus": 0,
                "permissions": {
                    "host": true
                }
            }
        ],
        "status": 0
    },
    "86039816": {
        "id": 86039816,
        "topicName": "",
        "members": [],
        "status": 0
    },
    "86284341": {
        "id": 86284341,
        "topicName": "",
        "members": [],
        "status": 0
    },
    "131331111": {
        "id": 131331111,
        "topicName": "",
        "members": [
            {
                "id": "9bd11427-928e-44cc-b07e-b694f1e0f8e1",
                "socketId": "",
                "displayName": "",
                "currentRoom": 131331111,
                "userStatus": 0,
                "permissions": {
                    "host": true
                }
            }
        ],
        "status": 0
    },
    "131995012": {
        "id": 131995012,
        "topicName": "",
        "members": [
            {
                "id": "8d50a44a-82f9-4cd3-bf04-c7bb016f97e2",
                "socketId": "",
                "displayName": "",
                "currentRoom": 131995012,
                "userStatus": 0,
                "permissions": {
                    "host": true
                }
            }
        ],
        "status": 0
    },
    "242835642": {
        "id": 242835642,
        "topicName": "",
        "members": [
            {
                "id": "ab5fe995-0096-447e-88ad-a4dcb0c3099c",
                "socketId": "",
                "displayName": "",
                "currentRoom": 242835642,
                "userStatus": 0,
                "permissions": {
                    "host": true
                }
            },
            {
                "id": "9dab496d-3cae-42cb-8320-ff6c7be8d84d",
                "socketId": "",
                "displayName": "",
                "currentRoom": 242835642,
                "userStatus": 0,
                "permissions": {
                    "host": false
                }
            }
        ],
        "status": 0
    },
    "263534076": {
        "id": 263534076,
        "topicName": "",
        "members": [],
        "status": 0
    },
    "271347439": {
        "id": 271347439,
        "topicName": "",
        "members": [
            {
                "id": "4e37f75b-cd0d-4ef0-b6e3-dd66d91c4588",
                "socketId": "",
                "displayName": "",
                "currentRoom": 271347439,
                "userStatus": 0,
                "permissions": {
                    "host": true
                }
            }
        ],
        "status": 0
    },
    "274847148": {
        "id": 274847148,
        "topicName": "",
        "members": [],
        "status": 0
    },
    "302072548": {
        "id": 302072548,
        "topicName": "",
        "members": [
            {
                "id": "1241a8ff-6fd8-4d2c-83f5-1f1c2b1714dc",
                "socketId": "",
                "displayName": "",
                "currentRoom": 302072548,
                "userStatus": 0,
                "permissions": {
                    "host": true
                }
            }
        ],
        "status": 0
    },
    "307173035": {
        "id": 307173035,
        "topicName": "",
        "members": [
            {
                "id": "8368035b-b4b7-431d-ab06-0e39642e0a0c",
                "socketId": "",
                "displayName": "",
                "currentRoom": 307173035,
                "userStatus": 0,
                "permissions": {
                    "host": true
                }
            }
        ],
        "status": 0
    },
    "319899652": {
        "id": 319899652,
        "topicName": "",
        "members": [
            {
                "id": "aa995269-57be-4e10-8264-be8637317b59",
                "socketId": "",
                "displayName": "",
                "currentRoom": 319899652,
                "userStatus": 0,
                "permissions": {
                    "host": true
                }
            }
        ],
        "status": 0
    },
    "337590088": {
        "id": 337590088,
        "topicName": "",
        "members": [],
        "status": 0
    },
    "405584373": {
        "id": 405584373,
        "topicName": "",
        "members": [],
        "status": 0
    },
    "420361746": {
        "id": 420361746,
        "topicName": "",
        "members": [
            {
                "id": "b24865ff-5886-4dca-82b9-5ecff1781c1d",
                "socketId": "",
                "displayName": "",
                "currentRoom": 420361746,
                "userStatus": 0,
                "permissions": {
                    "host": true
                }
            }
        ],
        "status": 0
    },
    "475614938": {
        "id": 475614938,
        "topicName": "",
        "members": [
            {
                "id": "df40df82-15aa-4a26-b540-507eedc47099",
                "socketId": "",
                "displayName": "",
                "currentRoom": 475614938,
                "userStatus": 0,
                "permissions": {
                    "host": true
                }
            }
        ],
        "status": 0
    },
    "646049820": {
        "id": 646049820,
        "topicName": "",
        "members": [],
        "status": 0
    },
    "690483883": {
        "id": 690483883,
        "topicName": "",
        "members": [
            {
                "id": "f0c8e429-0257-45c3-bcba-6c404e5bde78",
                "socketId": "",
                "displayName": "",
                "currentRoom": 690483883,
                "userStatus": 0,
                "permissions": {
                    "host": true
                }
            }
        ],
        "status": 0
    },
    "692168379": {
        "id": 692168379,
        "topicName": "",
        "members": [
            {
                "id": "0382f732-3cb9-419a-a364-5235ef35f5b4",
                "socketId": "",
                "displayName": "",
                "currentRoom": 692168379,
                "userStatus": 0,
                "permissions": {
                    "host": true
                }
            }
        ],
        "status": 0
    },
    "742967090": {
        "id": 742967090,
        "topicName": "",
        "members": [
            {
                "id": "6eee5fdb-3fcb-4a4a-b6e8-6b0753e6dd76",
                "socketId": "",
                "displayName": "",
                "currentRoom": 742967090,
                "userStatus": 0,
                "permissions": {
                    "host": true
                }
            }
        ],
        "status": 0
    },
    "751723977": {
        "id": 751723977,
        "topicName": "",
        "members": [
            {
                "id": "3b560d9f-3045-4276-bff7-3ad283c749f1",
                "socketId": "",
                "displayName": "",
                "currentRoom": 751723977,
                "userStatus": 0,
                "permissions": {
                    "host": true
                }
            }
        ],
        "status": 0
    },
    "765987458": {
        "id": 765987458,
        "topicName": "",
        "members": [
            {
                "id": "944aa202-c97c-4488-ae21-d75513c0444a",
                "socketId": "",
                "displayName": "",
                "currentRoom": 765987458,
                "userStatus": 0,
                "permissions": {
                    "host": true
                }
            }
        ],
        "status": 0
    },
    "872919721": {
        "id": 872919721,
        "topicName": "",
        "members": [
            {
                "id": "9428897d-a223-4c99-84a0-964fa661f23f",
                "socketId": "",
                "displayName": "",
                "currentRoom": 872919721,
                "userStatus": 0,
                "permissions": {
                    "host": true
                }
            }
        ],
        "status": 0
    },
    "876247373": {
        "id": 876247373,
        "topicName": "",
        "members": [],
        "status": 0
    },
    "897479849": {
        "id": 897479849,
        "topicName": "",
        "members": [],
        "status": 0
    },
    "948620702": {
        "id": 948620702,
        "topicName": "",
        "members": [
            {
                "id": "f2116522-024e-46c8-a10c-e3084ed9b674",
                "socketId": "",
                "displayName": "",
                "currentRoom": 948620702,
                "userStatus": 0,
                "permissions": {
                    "host": true
                }
            }
        ],
        "status": 0
    }
}